pywikipathways/__init__.py
pywikipathways/_version.py
pywikipathways/download_pathway_archive.py
pywikipathways/find_pathway_by_text.py
pywikipathways/find_pathways_by_literature.py
pywikipathways/find_pathways_by_xref.py
pywikipathways/get_curation_tags.py
pywikipathways/get_ontology_terms.py
pywikipathways/get_pathway.py
pywikipathways/get_pathway_history.py
pywikipathways/get_pathway_info.py
pywikipathways/get_recent_changes.py
pywikipathways/get_xref_list.py
pywikipathways/list_organisms.py
pywikipathways/list_pathways.py
pywikipathways/utilities.py
pywikipathways-0.0.3.dist-info/METADATA
pywikipathways-0.0.3.dist-info/WHEEL
pywikipathways-0.0.3.dist-info/licenses/LICENSE
pywikipathways-0.0.3.dist-info/RECORD
