Metadata-Version: 2.3
Name: pywikipathways
Version: 0.0.3
Summary: Python Client Package for WikiPathways.
Project-URL: Homepage, https://github.com/wikipathways/pywikipathways
Project-URL: Issues, https://github.com/wikipathways/pywikipathways/issues
Author-email: Kozo Nishida <kozo.nishida@gmail.com>
License-File: LICENSE
Classifier: Intended Audience :: Developers
Classifier: Intended Audience :: Science/Research
Classifier: License :: OSI Approved :: MIT License
Classifier: Operating System :: OS Independent
Classifier: Programming Language :: Python :: 3
Classifier: Programming Language :: Python :: 3.9
Classifier: Programming Language :: Python :: 3.10
Classifier: Programming Language :: Python :: 3.11
Classifier: Programming Language :: Python :: 3.12
Classifier: Topic :: Scientific/Engineering :: Bio-Informatics
Classifier: Topic :: Scientific/Engineering :: Information Analysis
Classifier: Topic :: Scientific/Engineering :: Mathematics
Classifier: Topic :: Scientific/Engineering :: Visualization
Requires-Python: >=3.9
Requires-Dist: lxml
Requires-Dist: pandas
Requires-Dist: requests
